Metadata-Version: 1.1
Name: gabrielegattiphysicslibrary
Version: 0.0.1
Summary: A short set of Physics formulas and constants
Home-page: UNKNOWN
Author: Gabriele Gatti
Author-email: gabrielegatti432@gmail.com
License: MIT
Keywords: physics
Platform: UNKNOWN
Classifier: Development Status :: 5 - Production/Stable
Classifier: Intended Audience :: Education
Classifier: Operating System :: Microsoft :: Windows :: Windows 10
Classifier: License :: OSI Approved :: MIT License
Classifier: Programming Language :: Python :: 3
